Workbook

Sheet 0 - Setup (Lists)
M1: Customer Reference | P1: Opporunity Reference
B2: Sales Pipeline Stages | C2: Probability % | E2: Status | G2: Sales Rep | I2: Activity Types | K2: Lead Source | M2: =IFERROR(__xludf.DUMMYFUNCTION("FILTER({'1 - Customers'!B2:B22, '1 - Customers'!C2:C22}, '1 - Customers'!B2:B22 <> """")"),"Client ID") -> Client ID | N2: =IFERROR(__xludf.DUMMYFUNCTION("""COMPUTED_VALUE"""),"Name") -> Name | P2: Opportunity ID | Q2: Opportunity Name | R2: Client ID | S2: Client Name
B3: Prospecting | C3: 0.1 | E3: New | G3: John Smith | I3: Call | K3: Website | M3: =IFERROR(__xludf.DUMMYFUNCTION("""COMPUTED_VALUE"""),"C001") -> C001 | N3: =IFERROR(__xludf.DUMMYFUNCTION("""COMPUTED_VALUE"""),"Alice Chen") -> Alice Chen | P3: {=_xlfn._xlws.FILTER( _xlfn.HSTACK(tblSalesPipeline[Opportunity ID], tblSalesPipeline[Opportunity Name], tblSalesPipeline[Client ID], tblSalesPipeline[Client Name]), tblSalesPipeline[Opportunity ID] <> "" )} -> OPP-001 | Q3: Consulting Services Proposal | R3: C003 | S3: Emma Brooks
B4: Qualification/Needs Assessment | C4: 0.25 | E4: Contacted | G4: Nick Miller | I4: Email | K4: Social Media | M4: =IFERROR(__xludf.DUMMYFUNCTION("""COMPUTED_VALUE"""),"C002") -> C002 | N4: =IFERROR(__xludf.DUMMYFUNCTION("""COMPUTED_VALUE"""),"Ethan Park") -> Ethan Park | P4: OPP-002 | Q4: Logistics Support Services | R4: C004 | S4: Marcus Bennett
B5: Proposal/Demo | C5: 0.5 | E5: Working | G5: Winston Bishop | I5: Meeting | K5: Referral | M5: =IFERROR(__xludf.DUMMYFUNCTION("""COMPUTED_VALUE"""),"C003") -> C003 | N5: =IFERROR(__xludf.DUMMYFUNCTION("""COMPUTED_VALUE"""),"Emma Brooks") -> Emma Brooks | P5: OPP-003 | Q5: Legal Services Engagement | R5: C006 | S5: Daniel Rodriguez
B6: Negotiation | C6: 0.75 | E6: Qualified | G6: Cecilia Schmidt | I6: Follow-Up | K6: Networking | M6: =IFERROR(__xludf.DUMMYFUNCTION("""COMPUTED_VALUE"""),"C004") -> C004 | N6: =IFERROR(__xludf.DUMMYFUNCTION("""COMPUTED_VALUE"""),"Marcus Bennett") -> Marcus Bennett | P6: OPP-004 | Q6: Design Project Scope | R6: C009 | S6: Isabella Rossi
B7: Closed Won | C7: 1 | E7: Unqualified | G7: Jessica Night | I7: Demo | K7: Email Campaign | M7: =IFERROR(__xludf.DUMMYFUNCTION("""COMPUTED_VALUE"""),"C005") -> C005 | N7: =IFERROR(__xludf.DUMMYFUNCTION("""COMPUTED_VALUE"""),"Chloe Nguyen") -> Chloe Nguyen | P7: OPP-005 | Q7: Custom Consulting Package | R7: C011 | S7: Maya Singh
B8: Closed Lost | C8: 0 | E8: Customer | I8: Proposal Sent | K8: LinkedIn | M8: =IFERROR(__xludf.DUMMYFUNCTION("""COMPUTED_VALUE"""),"C006") -> C006 | N8: =IFERROR(__xludf.DUMMYFUNCTION("""COMPUTED_VALUE"""),"Daniel Rodriguez") -> Daniel Rodriguez | P8: OPP-006 | Q8: Custom Consulting Package | R8: C014 | S8: Jackson Lee
E9: Inactive | I9: Website Form Submission | K9: Paid Ads | M9: =IFERROR(__xludf.DUMMYFUNCTION("""COMPUTED_VALUE"""),"C007") -> C007 | N9: =IFERROR(__xludf.DUMMYFUNCTION("""COMPUTED_VALUE"""),"Sophia Patel") -> Sophia Patel | P9: OPP-007 | Q9: Operations Consulting | R9: C015 | S9: Nina Kapoor
I10: Note | K10: Organic Search | M10: =IFERROR(__xludf.DUMMYFUNCTION("""COMPUTED_VALUE"""),"C008") -> C008 | N10: =IFERROR(__xludf.DUMMYFUNCTION("""COMPUTED_VALUE"""),"Liam O’Connor") -> Liam O’Connor
I11: Other | K11: Event / Webinar | M11: =IFERROR(__xludf.DUMMYFUNCTION("""COMPUTED_VALUE"""),"C009") -> C009 | N11: =IFERROR(__xludf.DUMMYFUNCTION("""COMPUTED_VALUE"""),"Isabella Rossi") -> Isabella Rossi
K12: Cold Outreach | M12: =IFERROR(__xludf.DUMMYFUNCTION("""COMPUTED_VALUE"""),"C010") -> C010 | N12: =IFERROR(__xludf.DUMMYFUNCTION("""COMPUTED_VALUE"""),"Noah Kim") -> Noah Kim
K13: Existing Customer | M13: =IFERROR(__xludf.DUMMYFUNCTION("""COMPUTED_VALUE"""),"C011") -> C011 | N13: =IFERROR(__xludf.DUMMYFUNCTION("""COMPUTED_VALUE"""),"Maya Singh") -> Maya Singh
K14: Partner / Affiliate | M14: =IFERROR(__xludf.DUMMYFUNCTION("""COMPUTED_VALUE"""),"C012") -> C012 | N14: =IFERROR(__xludf.DUMMYFUNCTION("""COMPUTED_VALUE"""),"Oliver Grant") -> Oliver Grant
M15: =IFERROR(__xludf.DUMMYFUNCTION("""COMPUTED_VALUE"""),"C013") -> C013 | N15: =IFERROR(__xludf.DUMMYFUNCTION("""COMPUTED_VALUE"""),"Ava Martinez") -> Ava Martinez
M16: =IFERROR(__xludf.DUMMYFUNCTION("""COMPUTED_VALUE"""),"C014") -> C014 | N16: =IFERROR(__xludf.DUMMYFUNCTION("""COMPUTED_VALUE"""),"Jackson Lee") -> Jackson Lee
M17: =IFERROR(__xludf.DUMMYFUNCTION("""COMPUTED_VALUE"""),"C015") -> C015 | N17: =IFERROR(__xludf.DUMMYFUNCTION("""COMPUTED_VALUE"""),"Nina Kapoor") -> Nina Kapoor

Sheet 1 - Customers
B2: Client ID | C2: Name | D2: Email | E2: Phone # | F2: Company | G2: Lead Source | H2: Sales Rep | I2: Lead Status | J2: Last Contact Date | K2: Created Date | L2: Notes | S2: Helper_ID
B3: C001 | C3: Alice Chen | D3: alice.chen@example.com | E3: 416-555-1021 | F3: Chen Wellness | G3: Website | H3: Winston Bishop | I3: New | J3: =IFERROR(__xludf.DUMMYFUNCTION("IFERROR( MAX( FILTER('3 - Activity Timeline'!E3:E18, '3 - Activity Timeline'!B3:B18 = B3) ), """")"),45938) -> 45938 | K3: 45928 | L3: Requested info on pricing | S3: =IF(B3="","",VALUE(MID(B3,2,10))) -> 1
B4: C002 | C4: Ethan Park | D4: ethan.park@example.com | E4: 647-555-3345 | F4: Park Consulting | G4: LinkedIn | H4: Winston Bishop | I4: Contacted | J4: =IFERROR(__xludf.DUMMYFUNCTION("IFERROR( MAX( FILTER('3 - Activity Timeline'!E4:E18, '3 - Activity Timeline'!B4:B18 = B4) ), """")"),45940) -> 45940 | K4: 45931 | L4: Initial outreach sent | S4: =IF(B4="","",VALUE(MID(B4,2,10))) -> 2
B5: C003 | C5: Emma Brooks | D5: emma.brooks@example.com | E5: 416-555-7789 | F5: Brooks Creative | G5: Referral | H5: John Smith | I5: Qualified | J5: =IFERROR(__xludf.DUMMYFUNCTION("IFERROR( MAX( FILTER('3 - Activity Timeline'!E5:E18, '3 - Activity Timeline'!B5:B18 = B5) ), """")"),45945) -> 45945 | K5: 45936 | L5: Referred by existing client | S5: =IF(B5="","",VALUE(MID(B5,2,10))) -> 3
B6: C004 | C6: Marcus Bennett | D6: marcus.bennett@example.com | E6: 905-555-2211 | F6: Bennett Logistics | G6: Networking | H6: Winston Bishop | I6: Qualified | J6: =IFERROR(__xludf.DUMMYFUNCTION("IFERROR( MAX( FILTER('3 - Activity Timeline'!E6:E18, '3 - Activity Timeline'!B6:B18 = B6) ), """")"),45986) -> 45986 | K6: 45971 | L6: Met at networking event | S6: =IF(B6="","",VALUE(MID(B6,2,10))) -> 4
B7: C005 | C7: Chloe Nguyen | D7: chloe.nguyen@example.com | E7: 647-555-9087 | F7: Nguyen Marketing | G7: Website | H7: Cecilia Schmidt | I7: Contacted | J7: 45968 | K7: 45976 | L7: Downloaded brochure | S7: =IF(B7="","",VALUE(MID(B7,2,10))) -> 5
B8: C006 | C8: Daniel Rodriguez | D8: daniel.r@example.com | E8: 416-555-6643 | F8: Rodriguez Law | G8: Referral | H8: Winston Bishop | I8: Qualified | J8: 45969 | K8: 45979 | L8: Needs proposal for services | S8: =IF(B8="","",VALUE(MID(B8,2,10))) -> 6
B9: C007 | C9: Sophia Patel | D9: sophia.patel@example.com | E9: 647-555-1129 | F9: Patel Health | G9: Referral | H9: Jessica Night | I9: Unqualified | J9: 45970 | K9: 45964 | L9: No budget confirmed yet | S9: =IF(B9="","",VALUE(MID(B9,2,10))) -> 7
B10: C008 | C10: Liam O’Connor | D10: liam.oconnor@example.com | E10: 905-555-4490 | F10: O’Connor Finance | G10: LinkedIn | H10: Winston Bishop | I10: Contacted | J10: 45971 | K10: 45966 | L10: Follow-up scheduled | S10: =IF(B10="","",VALUE(MID(B10,2,10))) -> 8
B11: C009 | C11: Isabella Rossi | D11: isabella.rossi@example.com | E11: 416-555-7301 | F11: Rossi Designs | G11: Website | H11: Nick Miller | I11: Qualified | J11: 45972 | K11: 45968 | L11: Interested in premium plan | S11: =IF(B11="","",VALUE(MID(B11,2,10))) -> 9
B12: C010 | C12: Noah Kim | D12: noah.kim@example.com | E12: 647-555-8844 | F12: Kim Analytics | G12: Email Campaign | H12: Winston Bishop | I12: Contacted | J12: 45973 | K12: 45970 | L12: Opened campaign email | S12: =IF(B12="","",VALUE(MID(B12,2,10))) -> 10
B13: C011 | C13: Maya Singh | D13: maya.singh@example.com | E13: 416-555-3912 | F13: Singh Consulting | G13: Referral | H13: John Smith | I13: Qualified | J13: 45974 | K13: 45972 | L13: Discovery call completed | S13: =IF(B13="","",VALUE(MID(B13,2,10))) -> 11
B14: C012 | C14: Oliver Grant | D14: oliver.grant@example.com | E14: 905-555-6108 | F14: Grant Solutions | G14: LinkedIn | H14: Winston Bishop | I14: Unqualified | J14: 45975 | K14: 45973 | L14: No response yet | S14: =IF(B14="","",VALUE(MID(B14,2,10))) -> 12
B15: C013 | C15: Ava Martinez | D15: ava.martinez@example.com | E15: 647-555-5420 | F15: Martinez Co. | G15: Website | H15: Jessica Night | I15: Contacted | J15: 46007 | K15: 45992 | L15: Requested demo | S15: =IF(B15="","",VALUE(MID(B15,2,10))) -> 13
B16: C014 | C16: Jackson Lee | D16: jackson.lee@example.com | E16: 416-555-9734 | F16: Lee Enterprises | G16: Networking | H16: Winston Bishop | I16: Qualified | J16: 46008 | K16: 46001 | L16: Strong interest expressed | S16: =IF(B16="","",VALUE(MID(B16,2,10))) -> 14
B17: C015 | C17: Nina Kapoor | D17: nina.kapoor@example.com | E17: 647-555-6632 | F17: Kapoor Wellness | G17: Referral | H17: Nick Miller | I17: Qualified | J17: 46009 | K17: 46006 | L17: Proposal requested | S17: =IF(B17="","",VALUE(MID(B17,2,10))) -> 15

Sheet 2 - Sales Pipeline
B2: Client ID | C2: Client Name | D2: Stage | E2: Opportunity ID | F2: Opportunity Name | G2: Assigned To | H2: Next Action | I2: Next Action Due Date | J2: Created Date | K2: Probability % | L2: Forecast Value | M2: Value | N2: Expected Close Date | S2: Helper_Col
B3: C003 | C3: =IF(B3="","", _xlfn.XLOOKUP(B3, '0 - Setup (Lists)'!M:M, '0 - Setup (Lists)'!N:N)) -> Emma Brooks | D3: Qualification/Needs Assessment | E3: OPP-001 | F3: Consulting Services Proposal | G3: John Smith | H3: Prepare proposal | I3: 46039 | J3: 45994 | K3: =IF(B3="","", _xlfn.XLOOKUP('2 - Sales Pipeline'!D3,Stages_List[Sales Pipeline Stages], Stages_List[Probability %])) -> 0.25 | L3: =IFERROR(M3 * K3, "") -> 1250 | M3: 5000 | N3: 46058 | S3: 1
B4: C004 | C4: =IF(B4="","", _xlfn.XLOOKUP(B4, '0 - Setup (Lists)'!M:M, '0 - Setup (Lists)'!N:N)) -> Marcus Bennett | D4: Closed Lost | E4: OPP-002 | F4: Logistics Support Services | G4: John Smith | H4: Send follow-up email | I4: 46039 | J4: 45981 | K4: =IF(B4="","", _xlfn.XLOOKUP('2 - Sales Pipeline'!D4,Stages_List[Sales Pipeline Stages], Stages_List[Probability %])) -> 0 | L4: =IFERROR(M4 * K4, "") -> 0 | M4: 6000 | N4: 46063 | S4: 2
B5: C006 | C5: =IF(B5="","", _xlfn.XLOOKUP(B5, '0 - Setup (Lists)'!M:M, '0 - Setup (Lists)'!N:N)) -> Daniel Rodriguez | D5: Proposal/Demo | E5: OPP-003 | F5: Legal Services Engagement | G5: John Smith | H5: Send formal proposal | I5: 46043 | J5: 46014 | K5: =IF(B5="","", _xlfn.XLOOKUP('2 - Sales Pipeline'!D5,Stages_List[Sales Pipeline Stages], Stages_List[Probability %])) -> 0.5 | L5: =IFERROR(M5 * K5, "") -> 2000 | M5: 4000 | N5: 46068 | S5: 3
B6: C009 | C6: =IF(B6="","", _xlfn.XLOOKUP(B6, '0 - Setup (Lists)'!M:M, '0 - Setup (Lists)'!N:N)) -> Isabella Rossi | D6: Closed Won | E6: OPP-004 | F6: Design Project Scope | G6: John Smith | H6: Follow up on pricing | I6: 46050 | J6: 45973 | K6: =IF(B6="","", _xlfn.XLOOKUP('2 - Sales Pipeline'!D6,Stages_List[Sales Pipeline Stages], Stages_List[Probability %])) -> 1 | L6: =IFERROR(M6 * K6, "") -> 3500 | M6: 3500 | N6: 46009 | S6: 4
B7: C011 | C7: =IF(B7="","", _xlfn.XLOOKUP(B7, '0 - Setup (Lists)'!M:M, '0 - Setup (Lists)'!N:N)) -> Maya Singh | D7: Closed Won | E7: OPP-005 | F7: Custom Consulting Package | G7: John Smith | H7: Negotiate final terms | I7: 46052 | J7: 45979 | K7: =IF(B7="","", _xlfn.XLOOKUP('2 - Sales Pipeline'!D7,Stages_List[Sales Pipeline Stages], Stages_List[Probability %])) -> 1 | L7: =IFERROR(M7 * K7, "") -> 6000 | M7: 6000 | N7: 45989 | S7: 5
B8: C014 | C8: =IF(B8="","", _xlfn.XLOOKUP(B8, '0 - Setup (Lists)'!M:M, '0 - Setup (Lists)'!N:N)) -> Jackson Lee | D8: Closed Lost | E8: OPP-006 | F8: Custom Consulting Package | G8: John Smith | H8: Send proposal draft | I8: 46051 | J8: 45980 | K8: =IF(B8="","", _xlfn.XLOOKUP('2 - Sales Pipeline'!D8,Stages_List[Sales Pipeline Stages], Stages_List[Probability %])) -> 0 | L8: =IFERROR(M8 * K8, "") -> 0 | M8: 5000 | N8: 46071 | S8: 6
B9: C015 | C9: =IF(B9="","", _xlfn.XLOOKUP(B9, '0 - Setup (Lists)'!M:M, '0 - Setup (Lists)'!N:N)) -> Nina Kapoor | D9: Closed Won | E9: OPP-007 | F9: Operations Consulting | G9: John Smith | H9: Prepare proposal | I9: 46053 | J9: 45952 | K9: =IF(B9="","", _xlfn.XLOOKUP('2 - Sales Pipeline'!D9,Stages_List[Sales Pipeline Stages], Stages_List[Probability %])) -> 1 | L9: =IFERROR(M9 * K9, "") -> 4500 | M9: 4500 | N9: 45961 | S9: 7

Sheet 3 - Activity Timeline
B2: Client ID | C2: Client Name | D2: Opportunity ID | E2: Date of Interaction | F2: Type of Interaction | G2: Summary of Interaction | H2: Next Steps | I2: Follow-Up Date | J2: Overdue Status
B3: C001 | C3: =IF(B3="","", _xlfn.XLOOKUP(B3, '0 - Setup (Lists)'!M:M, '0 - Setup (Lists)'!N:N)) -> Alice Chen | E3: 45936 | F3: Website Form Submission | G3: Submitted website form requesting pricing | H3: Review inquiry and respond | I3: 46032 | J3: =IF(tblActivityTimeline[[#This Row],[Follow-Up Date]]="","", IF(tblActivityTimeline[[#This Row],[Follow-Up Date]] < TODAY(),"Overdue","Good") ) -> Good
B4: C001 | C4: =IF(B4="","", _xlfn.XLOOKUP(B4, '0 - Setup (Lists)'!M:M, '0 - Setup (Lists)'!N:N)) -> Alice Chen | E4: 45938 | F4: Email | G4: Sent pricing overview and service options | H4: Schedule discovery call | I4: 46034 | J4: =IF(tblActivityTimeline[[#This Row],[Follow-Up Date]]="","", IF(tblActivityTimeline[[#This Row],[Follow-Up Date]] < TODAY(),"Overdue","Good") ) -> Good
B5: C002 | C5: =IF(B5="","", _xlfn.XLOOKUP(B5, '0 - Setup (Lists)'!M:M, '0 - Setup (Lists)'!N:N)) -> Ethan Park | E5: 45940 | F5: Email | G5: Initial outreach via LinkedIn message | H5: Wait for response | I5: 46036 | J5: =IF(tblActivityTimeline[[#This Row],[Follow-Up Date]]="","", IF(tblActivityTimeline[[#This Row],[Follow-Up Date]] < TODAY(),"Overdue","Good") ) -> Good
B6: C003 | C6: =IF(B6="","", _xlfn.XLOOKUP(B6, '0 - Setup (Lists)'!M:M, '0 - Setup (Lists)'!N:N)) -> Emma Brooks | E6: 45943 | F6: Call | G6: Introductory call to discuss referral background | H6: Send service overview | I6: 46037 | J6: =IF(tblActivityTimeline[[#This Row],[Follow-Up Date]]="","", IF(tblActivityTimeline[[#This Row],[Follow-Up Date]] < TODAY(),"Overdue","Good") ) -> Good
B7: C003 | C7: =IF(B7="","", _xlfn.XLOOKUP(B7, '0 - Setup (Lists)'!M:M, '0 - Setup (Lists)'!N:N)) -> Emma Brooks | E7: 45945 | F7: Email | G7: Sent service overview PDF | H7: Schedule discovery meeting | I7: 46039 | J7: =IF(tblActivityTimeline[[#This Row],[Follow-Up Date]]="","", IF(tblActivityTimeline[[#This Row],[Follow-Up Date]] < TODAY(),"Overdue","Good") ) -> Good
B8: C004 | C8: =IF(B8="","", _xlfn.XLOOKUP(B8, '0 - Setup (Lists)'!M:M, '0 - Setup (Lists)'!N:N)) -> Marcus Bennett | E8: 45947 | F8: Meeting | G8: Met at networking event; discussed logistics needs | H8: Send follow-up email | I8: 46039 | J8: =IF(tblActivityTimeline[[#This Row],[Follow-Up Date]]="","", IF(tblActivityTimeline[[#This Row],[Follow-Up Date]] < TODAY(),"Overdue","Good") ) -> Good
B9: C005 | C9: =IF(B9="","", _xlfn.XLOOKUP(B9, '0 - Setup (Lists)'!M:M, '0 - Setup (Lists)'!N:N)) -> Chloe Nguyen | E9: 45950 | F9: Website Form Submission | G9: Downloaded brochure from website | H9: Reach out via email | I9: 46040 | J9: =IF(tblActivityTimeline[[#This Row],[Follow-Up Date]]="","", IF(tblActivityTimeline[[#This Row],[Follow-Up Date]] < TODAY(),"Overdue","Good") ) -> Good
B10: C005 | C10: =IF(B10="","", _xlfn.XLOOKUP(B10, '0 - Setup (Lists)'!M:M, '0 - Setup (Lists)'!N:N)) -> Chloe Nguyen | E10: 45952 | F10: Email | G10: Follow-up email after brochure download | H10: Confirm interest level | I10: 46042 | J10: =IF(tblActivityTimeline[[#This Row],[Follow-Up Date]]="","", IF(tblActivityTimeline[[#This Row],[Follow-Up Date]] < TODAY(),"Overdue","Good") ) -> Good
B11: C006 | C11: =IF(B11="","", _xlfn.XLOOKUP(B11, '0 - Setup (Lists)'!M:M, '0 - Setup (Lists)'!N:N)) -> Daniel Rodriguez | E11: 45954 | F11: Call | G11: Referral call to discuss legal service needs | H11: Prepare proposal outline | I11: 46043 | J11: =IF(tblActivityTimeline[[#This Row],[Follow-Up Date]]="","", IF(tblActivityTimeline[[#This Row],[Follow-Up Date]] < TODAY(),"Overdue","Good") ) -> Good
B12: C007 | C12: =IF(B12="","", _xlfn.XLOOKUP(B12, '0 - Setup (Lists)'!M:M, '0 - Setup (Lists)'!N:N)) -> Sophia Patel | E12: 45957 | F12: Call | G12: Intro call; budget not confirmed | H12: Check back next month | I12: 46058 | J12: =IF(tblActivityTimeline[[#This Row],[Follow-Up Date]]="","", IF(tblActivityTimeline[[#This Row],[Follow-Up Date]] < TODAY(),"Overdue","Good") ) -> Good
B13: C008 | C13: =IF(B13="","", _xlfn.XLOOKUP(B13, '0 - Setup (Lists)'!M:M, '0 - Setup (Lists)'!N:N)) -> Liam O’Connor | E13: 45959 | F13: Email | G13: LinkedIn follow-up after connection | H13: Schedule intro call | I13: 46046 | J13: =IF(tblActivityTimeline[[#This Row],[Follow-Up Date]]="","", IF(tblActivityTimeline[[#This Row],[Follow-Up Date]] < TODAY(),"Overdue","Good") ) -> Good
B14: C009 | C14: =IF(B14="","", _xlfn.XLOOKUP(B14, '0 - Setup (Lists)'!M:M, '0 - Setup (Lists)'!N:N)) -> Isabella Rossi | E14: 45964 | F14: Call | G14: Discussed design project scope | H14: Send pricing tiers | I14: 46047 | J14: =IF(tblActivityTimeline[[#This Row],[Follow-Up Date]]="","", IF(tblActivityTimeline[[#This Row],[Follow-Up Date]] < TODAY(),"Overdue","Good") ) -> Good
... B21: C015 | C21: =IF(B21="","", _xlfn.XLOOKUP(B21, '0 - Setup (Lists)'!M:M, '0 - Setup (Lists)'!N:N)) -> Nina Kapoor | E21: 45983 | F21: Call | G21: Discovery call completed | H21: Prepare proposal | I21: 46053 | J21: =IF(tblActivityTimeline[[#This Row],[Follow-Up Date]]="","", IF(tblActivityTimeline[[#This Row],[Follow-Up Date]] < TODAY(),"Overdue","Good") ) -> Good
B22: C004 | C22: =IF(B22="","", _xlfn.XLOOKUP(B22, '0 - Setup (Lists)'!M:M, '0 - Setup (Lists)'!N:N)) -> Marcus Bennett | E22: 45986 | F22: Email | G22: Deal marked as Closed Lost — proposal declined | J22: =IF(tblActivityTimeline[[#This Row],[Follow-Up Date]]="","", IF(tblActivityTimeline[[#This Row],[Follow-Up Date]] < TODAY(),"Overdue","Good") )
B23: C014 | C23: =IF(B23="","", _xlfn.XLOOKUP(B23, '0 - Setup (Lists)'!M:M, '0 - Setup (Lists)'!N:N)) -> Jackson Lee | E23: 45989 | F23: Call | G23: Deal marked as Closed Lost — proposal declined | J23: =IF(tblActivityTimeline[[#This Row],[Follow-Up Date]]="","", IF(tblActivityTimeline[[#This Row],[Follow-Up Date]] < TODAY(),"Overdue","Good") )
B24: C009 | C24: =IF(B24="","", _xlfn.XLOOKUP(B24, '0 - Setup (Lists)'!M:M, '0 - Setup (Lists)'!N:N)) -> Isabella Rossi | E24: 45993 | F24: Email | G24: Deal marked as Closed Won — contract signed | J24: =IF(tblActivityTimeline[[#This Row],[Follow-Up Date]]="","", IF(tblActivityTimeline[[#This Row],[Follow-Up Date]] < TODAY(),"Overdue","Good") )
B25: C011 | C25: =IF(B25="","", _xlfn.XLOOKUP(B25, '0 - Setup (Lists)'!M:M, '0 - Setup (Lists)'!N:N)) -> Maya Singh | E25: 45996 | F25: Meeting | G25: Deal marked as Closed Won — contract signed | J25: =IF(tblActivityTimeline[[#This Row],[Follow-Up Date]]="","", IF(tblActivityTimeline[[#This Row],[Follow-Up Date]] < TODAY(),"Overdue","Good") )
B26: C015 | C26: =IF(B26="","", _xlfn.XLOOKUP(B26, '0 - Setup (Lists)'!M:M, '0 - Setup (Lists)'!N:N)) -> Nina Kapoor | E26: 45999 | F26: Follow-Up | G26: Deal marked as Closed Won — contract signed | J26: =IF(tblActivityTimeline[[#This Row],[Follow-Up Date]]="","", IF(tblActivityTimeline[[#This Row],[Follow-Up Date]] < TODAY(),"Overdue","Good") )

Sheet 4 - Pivot Tables
A1: Number of Deals by Stage (Deal Volume Funnel) | D1: Stage | E1: Spacer | F1: Value
A2: Stage | B2: COUNTA of Opportunity ID | D2: =A3 -> Proposal/Demo | E2: =(MAX($F$2:$F$5) - F2) / 2 -> 1 | F2: =B3 -> 1
A3: Proposal/Demo | B3: 1 | D3: =A4 -> Qualification/Needs Assessment | E3: =(MAX($F$2:$F$5) - F3) / 2 -> 1 | F3: =B4 -> 1
A4: Qualification/Needs Assessment | B4: 1 | D4: =A5 -> Closed Lost | E4: =(MAX($F$2:$F$5) - F4) / 2 -> 0.5 | F4: =B5 -> 2
A5: Closed Lost | B5: 2 | D5: =A6 -> Closed Won | E5: =(MAX($F$2:$F$5) - F5) / 2 -> 0 | F5: =B6 -> 3
A6: Closed Won | B6: 3
A8: Total Deal Value by Stage (Revenue Funnel) | D8: Stage
A9: Stage | B9: Sum of Value | D9: =A10 -> Proposal/Demo | E9: Spacer | F9: Value
A10: Proposal/Demo | B10: 4000 | D10: =A11 -> Qualification/Needs Assessment | E10: =(MAX($F$10:$F$13) - F10) / 2 -> 5000 | F10: =B10 -> 4000
A11: Qualification/Needs Assessment | B11: 5000 | D11: =A12 -> Closed Lost | E11: =(MAX($F$10:$F$13) - F11) / 2 -> 4500 | F11: =B11 -> 5000
A12: Closed Lost | B12: 11000 | D12: =A13 -> Closed Won | E12: =(MAX($F$10:$F$13) - F12) / 2 -> 1500 | F12: =B12 -> 11000
A13: Closed Won | B13: 14000 | E13: =(MAX($F$10:$F$13) - F13) / 2 -> 0 | F13: =B13 -> 14000
A15: Win vs. Loss Ratio
A16: Stage | B16: Sum of Value
A17: Closed Lost | B17: 0.44
A18: Closed Won | B18: 0.56
A20: Stage | B20: Closed Won
A21: Monthly Revenue Trend
A22: Expected Close Date | B22: Sum of Value
A23: Oct | B23: 4500
A24: Nov | B24: 6000
A25: Dec | B25: 3500
A27: Top 5 Deals By Client
A28: Client Name | B28: Sum of Value
A29: Emma Brooks | B29: 5000
A30: Marcus Bennett | B30: 6000
A31: Daniel Rodriguez | B31: 4000
A32: Isabella Rossi | B32: 3500
A33: Maya Singh | B33: 6000
A34: Jackson Lee | B34: 5000
A35: Nina Kapoor | B35: 4500

Sheet 5 - Dashboard
B2: CRM & Sales Pipeline Dashboard
B4: =SUMIFS( '2 - Sales Pipeline'!M:M, '2 - Sales Pipeline'!D:D, "<>Closed Won", '2 - Sales Pipeline'!D:D, "<>Closed Lost" ) -> 9000 | G4: =SUMIF('2 - Sales Pipeline'!D:D,"Closed Won",'2 - Sales Pipeline'!M:M) / ( SUMIF('2 - Sales Pipeline'!D:D,"Closed Won",'2 - Sales Pipeline'!M:M) + SUMIF('2 - Sales Pipeline'!D:D,"Closed Lost",'2 - Sales Pipeline'!M:M) ) -> 0.56 | L4: =IFERROR( AVERAGEIF( '2 - Sales Pipeline'!D:D, "Closed Won", '2 - Sales Pipeline'!M:M ), 0 ) -> 4666.6667 | Q4: =IFERROR(__xludf.DUMMYFUNCTION("IFERROR(COUNTA(UNIQUE( FILTER( '1 - Customers'!B:B, '1 - Customers'!B:B<>"""", '1 - Customers'!K:K >= EOMONTH(TODAY(), -1) + 1, '1 - Customers'!K:K <= EOMONTH(TODAY(), 0) ) )),0)"),4) -> 4
B5: Pipeline Value (Open Deals Only) | G5: Win Rate (Value-Based) | L5: Average Deal Size (Closed Won) | Q5: New Clients (This Month)
